odoo/addons/l10n_es_facturae_efact/README.rst
odoo/addons/l10n_es_facturae_efact/__init__.py
odoo/addons/l10n_es_facturae_efact/__manifest__.py
odoo/addons/l10n_es_facturae_efact/components/__init__.py
odoo/addons/l10n_es_facturae_efact/components/edi_input_process_l10n_es_facturae_l10n_es_facturae_efact_update.py
odoo/addons/l10n_es_facturae_efact/data/efact_data.xml
odoo/addons/l10n_es_facturae_efact/i18n/ca.po
odoo/addons/l10n_es_facturae_efact/i18n/es.po
odoo/addons/l10n_es_facturae_efact/i18n/l10n_es_facturae_efact.pot
odoo/addons/l10n_es_facturae_efact/migrations/13.0.1.0.0/post-migration.py
odoo/addons/l10n_es_facturae_efact/migrations/13.0.2.0.0/post-migration.py
odoo/addons/l10n_es_facturae_efact/models/__init__.py
odoo/addons/l10n_es_facturae_efact/models/account_move.py
odoo/addons/l10n_es_facturae_efact/models/edi_exchange_record.py
odoo/addons/l10n_es_facturae_efact/readme/CONFIG.rst
odoo/addons/l10n_es_facturae_efact/readme/CONTRIBUTORS.rst
odoo/addons/l10n_es_facturae_efact/readme/DESCRIPTION.rst
odoo/addons/l10n_es_facturae_efact/readme/INSTALL.rst
odoo/addons/l10n_es_facturae_efact/readme/ROADMAP.rst
odoo/addons/l10n_es_facturae_efact/static/description/icon.png
odoo/addons/l10n_es_facturae_efact/static/description/index.html
odoo/addons/l10n_es_facturae_efact/tests/__init__.py
odoo/addons/l10n_es_facturae_efact/tests/result.xml
odoo/addons/l10n_es_facturae_efact/tests/result_02.xml
odoo/addons/l10n_es_facturae_efact/tests/test_efact.py
odoo13_addon_l10n_es_facturae_efact-13.0.2.0.1.dist-info/METADATA
odoo13_addon_l10n_es_facturae_efact-13.0.2.0.1.dist-info/WHEEL
odoo13_addon_l10n_es_facturae_efact-13.0.2.0.1.dist-info/top_level.txt
odoo13_addon_l10n_es_facturae_efact-13.0.2.0.1.dist-info/RECORD
