Metadata-Version: 2.1
Name: odoo13-addon-l10n-es-facturae-efact
Version: 13.0.2.0.1
Summary: Envío de Factura-e a e.FACT
Home-page: https://github.com/OCA/l10n-spain
Author: Creu Blanca, Odoo Community Association (OCA)
Author-email: support@odoo-community.org
License: AGPL-3
Platform: UNKNOWN
Classifier: Programming Language :: Python
Classifier: Framework :: Odoo
Classifier: Framework :: Odoo :: 13.0
Classifier: License :: OSI Approved :: GNU Affero General Public License v3
Requires-Python: >=3.5
Requires-Dist: odoo13-addon-l10n-es-facturae-face
Requires-Dist: odoo (<13.1dev,>=13.0a)
Requires-Dist: paramiko
Requires-Dist: pyOpenSSL
Requires-Dist: xmlsec
